{"metadata": {"dbt_schema_version": "https://schemas.getdbt.com/dbt/run-results/v6.json", "dbt_version": "1.11.2", "generated_at": "2026-01-12T19:39:58.879161Z", "invocation_id": "e19b9061-f2b1-41dd-bd84-8133fa2875b1", "invocation_started_at": "2026-01-12T19:39:47.120918Z", "env": {}}, "results": [{"status": "pass", "timing": [{"name": "compile", "started_at": "2026-01-12T19:39:52.876568Z", "completed_at": "2026-01-12T19:39:52.922968Z"}, {"name": "execute", "started_at": "2026-01-12T19:39:52.925508Z", "completed_at": "2026-01-12T19:39:53.090464Z"}], "thread_id": "Thread-1 (worker)", "execution_time": 0.22226810455322266, "adapter_response": {"_message": "SELECT 1", "code": "SELECT", "rows_affected": 1}, "message": null, "failures": 0, "unique_id": "test.ecommerce_orders_analytics.accepted_values_fact_order_revenue_consistency_consistency_score_flag__Insufficient_Data__Volatile__Consistent__Stable.137844a448", "compiled": true, "compiled_code": "\n    \n    \n\nwith all_values as (\n\n    select\n        consistency_score_flag as value_field,\n        count(*) as n_records\n\n    from \"ecommerce_orders_analytics\".\"analytics\".\"fact_order_revenue_consistency\"\n    group by consistency_score_flag\n\n)\n\nselect *\nfrom all_values\nwhere value_field not in (\n    'Insufficient Data','Volatile','Consistent','Stable'\n)\n\n\n", "relation_name": null, "batch_results": null}, {"status": "pass", "timing": [{"name": "compile", "started_at": "2026-01-12T19:39:53.106201Z", "completed_at": "2026-01-12T19:39:53.120928Z"}, {"name": "execute", "started_at": "2026-01-12T19:39:53.122922Z", "completed_at": "2026-01-12T19:39:53.221652Z"}], "thread_id": "Thread-1 (worker)", "execution_time": 0.12145805358886719, "adapter_response": {"_message": "SELECT 1", "code": "SELECT", "rows_affected": 1}, "message": null, "failures": 0, "unique_id": "test.ecommerce_orders_analytics.accepted_values_fact_order_weekly_growth_growth_ratio_flag__Insufficient_Data__Improving__Declining__Stable.981fc688be", "compiled": true, "compiled_code": "\n    \n    \n\nwith all_values as (\n\n    select\n        growth_ratio_flag as value_field,\n        count(*) as n_records\n\n    from \"ecommerce_orders_analytics\".\"analytics\".\"fact_order_weekly_growth\"\n    group by growth_ratio_flag\n\n)\n\nselect *\nfrom all_values\nwhere value_field not in (\n    'Insufficient Data','Improving','Declining','Stable'\n)\n\n\n", "relation_name": null, "batch_results": null}, {"status": "pass", "timing": [{"name": "compile", "started_at": "2026-01-12T19:39:53.237966Z", "completed_at": "2026-01-12T19:39:53.250811Z"}, {"name": "execute", "started_at": "2026-01-12T19:39:53.251815Z", "completed_at": "2026-01-12T19:39:53.345326Z"}], "thread_id": "Thread-1 (worker)", "execution_time": 0.11339330673217773, "adapter_response": {"_message": "SELECT 1", "code": "SELECT", "rows_affected": 1}, "message": null, "failures": 0, "unique_id": "test.ecommerce_orders_analytics.dbt_utils_expression_is_true_int_weekly_customers_churned_customers_churned_customers_active_customers_prev_week.c070b97c50", "compiled": true, "compiled_code": "\n\n\n\nselect\n    1\nfrom \"ecommerce_orders_analytics\".\"analytics\".\"int_weekly_customers_churned_customers\"\n\nwhere not(churned_customers <= active_customers_prev_week)\n\n", "relation_name": null, "batch_results": null}, {"status": "pass", "timing": [{"name": "compile", "started_at": "2026-01-12T19:39:53.363018Z", "completed_at": "2026-01-12T19:39:53.378014Z"}, {"name": "execute", "started_at": "2026-01-12T19:39:53.379009Z", "completed_at": "2026-01-12T19:39:53.470269Z"}], "thread_id": "Thread-1 (worker)", "execution_time": 0.11417508125305176, "adapter_response": {"_message": "SELECT 1", "code": "SELECT", "rows_affected": 1}, "message": null, "failures": 0, "unique_id": "test.ecommerce_orders_analytics.dbt_utils_expression_is_true_int_weekly_customers_retained_customers_retained_customers_active_customers_prev_week.bef9b54145", "compiled": true, "compiled_code": "\n\n\n\nselect\n    1\nfrom \"ecommerce_orders_analytics\".\"analytics\".\"int_weekly_customers_retained_customers\"\n\nwhere not(retained_customers <= active_customers_prev_week)\n\n", "relation_name": null, "batch_results": null}, {"status": "pass", "timing": [{"name": "compile", "started_at": "2026-01-12T19:39:53.486279Z", "completed_at": "2026-01-12T19:39:53.503076Z"}, {"name": "execute", "started_at": "2026-01-12T19:39:53.504045Z", "completed_at": "2026-01-12T19:39:53.598644Z"}], "thread_id": "Thread-1 (worker)", "execution_time": 0.11836528778076172, "adapter_response": {"_message": "SELECT 1", "code": "SELECT", "rows_affected": 1}, "message": null, "failures": 0, "unique_id": "test.ecommerce_orders_analytics.not_null_fact_order_revenue_consistency_week_start.d314859889", "compiled": true, "compiled_code": "\n    \n    \n\n\n\nselect week_start\nfrom \"ecommerce_orders_analytics\".\"analytics\".\"fact_order_revenue_consistency\"\nwhere week_start is null\n\n\n", "relation_name": null, "batch_results": null}, {"status": "pass", "timing": [{"name": "compile", "started_at": "2026-01-12T19:39:53.613887Z", "completed_at": "2026-01-12T19:39:53.624889Z"}, {"name": "execute", "started_at": "2026-01-12T19:39:53.628293Z", "completed_at": "2026-01-12T19:39:53.722903Z"}], "thread_id": "Thread-1 (worker)", "execution_time": 0.1166989803314209, "adapter_response": {"_message": "SELECT 1", "code": "SELECT", "rows_affected": 1}, "message": null, "failures": 0, "unique_id": "test.ecommerce_orders_analytics.not_null_fact_order_revenue_consistency_weekly_revenue.567e09ca16", "compiled": true, "compiled_code": "\n    \n    \n\n\n\nselect weekly_revenue\nfrom \"ecommerce_orders_analytics\".\"analytics\".\"fact_order_revenue_consistency\"\nwhere weekly_revenue is null\n\n\n", "relation_name": null, "batch_results": null}, {"status": "pass", "timing": [{"name": "compile", "started_at": "2026-01-12T19:39:53.738550Z", "completed_at": "2026-01-12T19:39:53.750784Z"}, {"name": "execute", "started_at": "2026-01-12T19:39:53.752780Z", "completed_at": "2026-01-12T19:39:53.844390Z"}], "thread_id": "Thread-1 (worker)", "execution_time": 0.11084365844726562, "adapter_response": {"_message": "SELECT 1", "code": "SELECT", "rows_affected": 1}, "message": null, "failures": 0, "unique_id": "test.ecommerce_orders_analytics.not_null_fact_order_weekly_growth_week_start.875cf34a98", "compiled": true, "compiled_code": "\n    \n    \n\n\n\nselect week_start\nfrom \"ecommerce_orders_analytics\".\"analytics\".\"fact_order_weekly_growth\"\nwhere week_start is null\n\n\n", "relation_name": null, "batch_results": null}, {"status": "pass", "timing": [{"name": "compile", "started_at": "2026-01-12T19:39:53.861651Z", "completed_at": "2026-01-12T19:39:53.871646Z"}, {"name": "execute", "started_at": "2026-01-12T19:39:53.872647Z", "completed_at": "2026-01-12T19:39:53.964318Z"}], "thread_id": "Thread-1 (worker)", "execution_time": 0.10992789268493652, "adapter_response": {"_message": "SELECT 1", "code": "SELECT", "rows_affected": 1}, "message": null, "failures": 0, "unique_id": "test.ecommerce_orders_analytics.not_null_fact_order_weekly_growth_weekly_revenue.dc3d48cf8f", "compiled": true, "compiled_code": "\n    \n    \n\n\n\nselect weekly_revenue\nfrom \"ecommerce_orders_analytics\".\"analytics\".\"fact_order_weekly_growth\"\nwhere weekly_revenue is null\n\n\n", "relation_name": null, "batch_results": null}, {"status": "pass", "timing": [{"name": "compile", "started_at": "2026-01-12T19:39:53.980237Z", "completed_at": "2026-01-12T19:39:53.991236Z"}, {"name": "execute", "started_at": "2026-01-12T19:39:53.994742Z", "completed_at": "2026-01-12T19:39:54.090197Z"}], "thread_id": "Thread-1 (worker)", "execution_time": 0.11621594429016113, "adapter_response": {"_message": "SELECT 1", "code": "SELECT", "rows_affected": 1}, "message": null, "failures": 0, "unique_id": "test.ecommerce_orders_analytics.not_null_fact_weekly_customers_churn_rate_week.38cadde261", "compiled": true, "compiled_code": "\n    \n    \n\n\n\nselect week\nfrom \"ecommerce_orders_analytics\".\"analytics\".\"fact_weekly_customers_churn_rate\"\nwhere week is null\n\n\n", "relation_name": null, "batch_results": null}, {"status": "pass", "timing": [{"name": "compile", "started_at": "2026-01-12T19:39:54.105485Z", "completed_at": "2026-01-12T19:39:54.118707Z"}, {"name": "execute", "started_at": "2026-01-12T19:39:54.119719Z", "completed_at": "2026-01-12T19:39:54.214091Z"}], "thread_id": "Thread-1 (worker)", "execution_time": 0.11563301086425781, "adapter_response": {"_message": "SELECT 1", "code": "SELECT", "rows_affected": 1}, "message": null, "failures": 0, "unique_id": "test.ecommerce_orders_analytics.not_null_fact_weekly_customers_retain_rate_week.cd58269bf8", "compiled": true, "compiled_code": "\n    \n    \n\n\n\nselect week\nfrom \"ecommerce_orders_analytics\".\"analytics\".\"fact_weekly_customers_retain_rate\"\nwhere week is null\n\n\n", "relation_name": null, "batch_results": null}, {"status": "pass", "timing": [{"name": "compile", "started_at": "2026-01-12T19:39:54.230050Z", "completed_at": "2026-01-12T19:39:54.241048Z"}, {"name": "execute", "started_at": "2026-01-12T19:39:54.244112Z", "completed_at": "2026-01-12T19:39:54.339903Z"}], "thread_id": "Thread-1 (worker)", "execution_time": 0.11562514305114746, "adapter_response": {"_message": "SELECT 1", "code": "SELECT", "rows_affected": 1}, "message": null, "failures": 0, "unique_id": "test.ecommerce_orders_analytics.not_null_int_weekly_active_customers_customer_id.22592433ff", "compiled": true, "compiled_code": "\n    \n    \n\n\n\nselect customer_id\nfrom \"ecommerce_orders_analytics\".\"analytics\".\"int_weekly_active_customers\"\nwhere customer_id is null\n\n\n", "relation_name": null, "batch_results": null}, {"status": "pass", "timing": [{"name": "compile", "started_at": "2026-01-12T19:39:54.355665Z", "completed_at": "2026-01-12T19:39:54.369780Z"}, {"name": "execute", "started_at": "2026-01-12T19:39:54.371748Z", "completed_at": "2026-01-12T19:39:54.477701Z"}], "thread_id": "Thread-1 (worker)", "execution_time": 0.1297304630279541, "adapter_response": {"_message": "SELECT 1", "code": "SELECT", "rows_affected": 1}, "message": null, "failures": 0, "unique_id": "test.ecommerce_orders_analytics.not_null_int_weekly_active_customers_lag_customer_id.64581edb95", "compiled": true, "compiled_code": "\n    \n    \n\n\n\nselect customer_id\nfrom \"ecommerce_orders_analytics\".\"analytics\".\"int_weekly_active_customers_lag\"\nwhere customer_id is null\n\n\n", "relation_name": null, "batch_results": null}, {"status": "pass", "timing": [{"name": "compile", "started_at": "2026-01-12T19:39:54.498241Z", "completed_at": "2026-01-12T19:39:54.511239Z"}, {"name": "execute", "started_at": "2026-01-12T19:39:54.513245Z", "completed_at": "2026-01-12T19:39:54.616915Z"}], "thread_id": "Thread-1 (worker)", "execution_time": 0.12667489051818848, "adapter_response": {"_message": "SELECT 1", "code": "SELECT", "rows_affected": 1}, "message": null, "failures": 0, "unique_id": "test.ecommerce_orders_analytics.not_null_int_weekly_active_customers_lag_week.97c0b9f754", "compiled": true, "compiled_code": "\n    \n    \n\n\n\nselect week\nfrom \"ecommerce_orders_analytics\".\"analytics\".\"int_weekly_active_customers_lag\"\nwhere week is null\n\n\n", "relation_name": null, "batch_results": null}, {"status": "pass", "timing": [{"name": "compile", "started_at": "2026-01-12T19:39:54.633949Z", "completed_at": "2026-01-12T19:39:54.646244Z"}, {"name": "execute", "started_at": "2026-01-12T19:39:54.648245Z", "completed_at": "2026-01-12T19:39:54.785293Z"}], "thread_id": "Thread-1 (worker)", "execution_time": 0.1613483428955078, "adapter_response": {"_message": "SELECT 1", "code": "SELECT", "rows_affected": 1}, "message": null, "failures": 0, "unique_id": "test.ecommerce_orders_analytics.not_null_int_weekly_active_customers_week.0082c3589d", "compiled": true, "compiled_code": "\n    \n    \n\n\n\nselect week\nfrom \"ecommerce_orders_analytics\".\"analytics\".\"int_weekly_active_customers\"\nwhere week is null\n\n\n", "relation_name": null, "batch_results": null}, {"status": "pass", "timing": [{"name": "compile", "started_at": "2026-01-12T19:39:54.811369Z", "completed_at": "2026-01-12T19:39:54.834232Z"}, {"name": "execute", "started_at": "2026-01-12T19:39:54.836236Z", "completed_at": "2026-01-12T19:39:54.955497Z"}], "thread_id": "Thread-1 (worker)", "execution_time": 0.1540212631225586, "adapter_response": {"_message": "SELECT 1", "code": "SELECT", "rows_affected": 1}, "message": null, "failures": 0, "unique_id": "test.ecommerce_orders_analytics.not_null_int_weekly_customers_churn_flag_customer_id.f81f5f91aa", "compiled": true, "compiled_code": "\n    \n    \n\n\n\nselect customer_id\nfrom \"ecommerce_orders_analytics\".\"analytics\".\"int_weekly_customers_churn_flag\"\nwhere customer_id is null\n\n\n", "relation_name": null, "batch_results": null}, {"status": "pass", "timing": [{"name": "compile", "started_at": "2026-01-12T19:39:54.979675Z", "completed_at": "2026-01-12T19:39:54.996172Z"}, {"name": "execute", "started_at": "2026-01-12T19:39:54.997178Z", "completed_at": "2026-01-12T19:39:55.092703Z"}], "thread_id": "Thread-1 (worker)", "execution_time": 0.12517929077148438, "adapter_response": {"_message": "SELECT 1", "code": "SELECT", "rows_affected": 1}, "message": null, "failures": 0, "unique_id": "test.ecommerce_orders_analytics.not_null_int_weekly_customers_churn_flag_week.58c9fd9f1a", "compiled": true, "compiled_code": "\n    \n    \n\n\n\nselect week\nfrom \"ecommerce_orders_analytics\".\"analytics\".\"int_weekly_customers_churn_flag\"\nwhere week is null\n\n\n", "relation_name": null, "batch_results": null}, {"status": "pass", "timing": [{"name": "compile", "started_at": "2026-01-12T19:39:55.111792Z", "completed_at": "2026-01-12T19:39:55.146318Z"}, {"name": "execute", "started_at": "2026-01-12T19:39:55.148327Z", "completed_at": "2026-01-12T19:39:55.254160Z"}], "thread_id": "Thread-1 (worker)", "execution_time": 0.146406888961792, "adapter_response": {"_message": "SELECT 1", "code": "SELECT", "rows_affected": 1}, "message": null, "failures": 0, "unique_id": "test.ecommerce_orders_analytics.not_null_int_weekly_customers_churned_customers_week.e49d6b4233", "compiled": true, "compiled_code": "\n    \n    \n\n\n\nselect week\nfrom \"ecommerce_orders_analytics\".\"analytics\".\"int_weekly_customers_churned_customers\"\nwhere week is null\n\n\n", "relation_name": null, "batch_results": null}, {"status": "pass", "timing": [{"name": "compile", "started_at": "2026-01-12T19:39:55.269785Z", "completed_at": "2026-01-12T19:39:55.301040Z"}, {"name": "execute", "started_at": "2026-01-12T19:39:55.301040Z", "completed_at": "2026-01-12T19:39:55.410403Z"}], "thread_id": "Thread-1 (worker)", "execution_time": 0.15624308586120605, "adapter_response": {"_message": "SELECT 1", "code": "SELECT", "rows_affected": 1}, "message": null, "failures": 0, "unique_id": "test.ecommerce_orders_analytics.not_null_int_weekly_customers_retain_flag_customer_id.4756d2a119", "compiled": true, "compiled_code": "\n    \n    \n\n\n\nselect customer_id\nfrom \"ecommerce_orders_analytics\".\"analytics\".\"int_weekly_customers_retain_flag\"\nwhere customer_id is null\n\n\n", "relation_name": null, "batch_results": null}, {"status": "pass", "timing": [{"name": "compile", "started_at": "2026-01-12T19:39:55.426036Z", "completed_at": "2026-01-12T19:39:55.441662Z"}, {"name": "execute", "started_at": "2026-01-12T19:39:55.441662Z", "completed_at": "2026-01-12T19:39:55.535405Z"}], "thread_id": "Thread-1 (worker)", "execution_time": 0.10936880111694336, "adapter_response": {"_message": "SELECT 1", "code": "SELECT", "rows_affected": 1}, "message": null, "failures": 0, "unique_id": "test.ecommerce_orders_analytics.not_null_int_weekly_customers_retain_flag_week.fc81280ff6", "compiled": true, "compiled_code": "\n    \n    \n\n\n\nselect week\nfrom \"ecommerce_orders_analytics\".\"analytics\".\"int_weekly_customers_retain_flag\"\nwhere week is null\n\n\n", "relation_name": null, "batch_results": null}, {"status": "pass", "timing": [{"name": "compile", "started_at": "2026-01-12T19:39:55.535405Z", "completed_at": "2026-01-12T19:39:55.551027Z"}, {"name": "execute", "started_at": "2026-01-12T19:39:55.551027Z", "completed_at": "2026-01-12T19:39:55.738555Z"}], "thread_id": "Thread-1 (worker)", "execution_time": 0.21874690055847168, "adapter_response": {"_message": "SELECT 1", "code": "SELECT", "rows_affected": 1}, "message": null, "failures": 0, "unique_id": "test.ecommerce_orders_analytics.not_null_int_weekly_customers_retained_customers_week.a3b824facf", "compiled": true, "compiled_code": "\n    \n    \n\n\n\nselect week\nfrom \"ecommerce_orders_analytics\".\"analytics\".\"int_weekly_customers_retained_customers\"\nwhere week is null\n\n\n", "relation_name": null, "batch_results": null}, {"status": "pass", "timing": [{"name": "compile", "started_at": "2026-01-12T19:39:55.754152Z", "completed_at": "2026-01-12T19:39:55.769788Z"}, {"name": "execute", "started_at": "2026-01-12T19:39:55.769788Z", "completed_at": "2026-01-12T19:39:55.863525Z"}], "thread_id": "Thread-1 (worker)", "execution_time": 0.10937285423278809, "adapter_response": {"_message": "SELECT 1", "code": "SELECT", "rows_affected": 1}, "message": null, "failures": 0, "unique_id": "test.ecommerce_orders_analytics.not_null_int_weekly_order_revenue_lag_1w_week_start.32097cdf19", "compiled": true, "compiled_code": "\n    \n    \n\n\n\nselect week_start\nfrom \"ecommerce_orders_analytics\".\"analytics\".\"int_weekly_order_revenue_lag_1w\"\nwhere week_start is null\n\n\n", "relation_name": null, "batch_results": null}, {"status": "pass", "timing": [{"name": "compile", "started_at": "2026-01-12T19:39:55.879159Z", "completed_at": "2026-01-12T19:39:55.894788Z"}, {"name": "execute", "started_at": "2026-01-12T19:39:55.894788Z", "completed_at": "2026-01-12T19:39:55.988531Z"}], "thread_id": "Thread-1 (worker)", "execution_time": 0.10937166213989258, "adapter_response": {"_message": "SELECT 1", "code": "SELECT", "rows_affected": 1}, "message": null, "failures": 0, "unique_id": "test.ecommerce_orders_analytics.not_null_int_weekly_order_revenue_lag_1w_weekly_revenue.e86ef59a2f", "compiled": true, "compiled_code": "\n    \n    \n\n\n\nselect weekly_revenue\nfrom \"ecommerce_orders_analytics\".\"analytics\".\"int_weekly_order_revenue_lag_1w\"\nwhere weekly_revenue is null\n\n\n", "relation_name": null, "batch_results": null}, {"status": "pass", "timing": [{"name": "compile", "started_at": "2026-01-12T19:39:56.004152Z", "completed_at": "2026-01-12T19:39:56.019781Z"}, {"name": "execute", "started_at": "2026-01-12T19:39:56.019781Z", "completed_at": "2026-01-12T19:39:56.113525Z"}], "thread_id": "Thread-1 (worker)", "execution_time": 0.10937309265136719, "adapter_response": {"_message": "SELECT 1", "code": "SELECT", "rows_affected": 1}, "message": null, "failures": 0, "unique_id": "test.ecommerce_orders_analytics.not_null_int_weekly_order_revenue_lag_4w_week_start.e1befcf2b7", "compiled": true, "compiled_code": "\n    \n    \n\n\n\nselect week_start\nfrom \"ecommerce_orders_analytics\".\"analytics\".\"int_weekly_order_revenue_lag_4w\"\nwhere week_start is null\n\n\n", "relation_name": null, "batch_results": null}, {"status": "pass", "timing": [{"name": "compile", "started_at": "2026-01-12T19:39:56.129150Z", "completed_at": "2026-01-12T19:39:56.129150Z"}, {"name": "execute", "started_at": "2026-01-12T19:39:56.129150Z", "completed_at": "2026-01-12T19:39:56.222899Z"}], "thread_id": "Thread-1 (worker)", "execution_time": 0.09374880790710449, "adapter_response": {"_message": "SELECT 1", "code": "SELECT", "rows_affected": 1}, "message": null, "failures": 0, "unique_id": "test.ecommerce_orders_analytics.not_null_int_weekly_order_revenue_lag_4w_weekly_revenue.476c59a98c", "compiled": true, "compiled_code": "\n    \n    \n\n\n\nselect weekly_revenue\nfrom \"ecommerce_orders_analytics\".\"analytics\".\"int_weekly_order_revenue_lag_4w\"\nwhere weekly_revenue is null\n\n\n", "relation_name": null, "batch_results": null}, {"status": "pass", "timing": [{"name": "compile", "started_at": "2026-01-12T19:39:56.238524Z", "completed_at": "2026-01-12T19:39:56.254165Z"}, {"name": "execute", "started_at": "2026-01-12T19:39:56.254165Z", "completed_at": "2026-01-12T19:39:56.332305Z"}], "thread_id": "Thread-1 (worker)", "execution_time": 0.10941505432128906, "adapter_response": {"_message": "SELECT 1", "code": "SELECT", "rows_affected": 1}, "message": null, "failures": 0, "unique_id": "test.ecommerce_orders_analytics.not_null_int_weekly_order_revenue_rolling_4w_week_start.3949685237", "compiled": true, "compiled_code": "\n    \n    \n\n\n\nselect week_start\nfrom \"ecommerce_orders_analytics\".\"analytics\".\"int_weekly_order_revenue_rolling_4w\"\nwhere week_start is null\n\n\n", "relation_name": null, "batch_results": null}, {"status": "pass", "timing": [{"name": "compile", "started_at": "2026-01-12T19:39:56.347939Z", "completed_at": "2026-01-12T19:39:56.363538Z"}, {"name": "execute", "started_at": "2026-01-12T19:39:56.363538Z", "completed_at": "2026-01-12T19:39:56.457273Z"}], "thread_id": "Thread-1 (worker)", "execution_time": 0.10933375358581543, "adapter_response": {"_message": "SELECT 1", "code": "SELECT", "rows_affected": 1}, "message": null, "failures": 0, "unique_id": "test.ecommerce_orders_analytics.not_null_int_weekly_order_revenue_rolling_4w_weekly_revenue.91e8be52ef", "compiled": true, "compiled_code": "\n    \n    \n\n\n\nselect weekly_revenue\nfrom \"ecommerce_orders_analytics\".\"analytics\".\"int_weekly_order_revenue_rolling_4w\"\nwhere weekly_revenue is null\n\n\n", "relation_name": null, "batch_results": null}, {"status": "pass", "timing": [{"name": "compile", "started_at": "2026-01-12T19:39:56.472906Z", "completed_at": "2026-01-12T19:39:56.488535Z"}, {"name": "execute", "started_at": "2026-01-12T19:39:56.488535Z", "completed_at": "2026-01-12T19:39:56.582307Z"}], "thread_id": "Thread-1 (worker)", "execution_time": 0.10940098762512207, "adapter_response": {"_message": "SELECT 1", "code": "SELECT", "rows_affected": 1}, "message": null, "failures": 0, "unique_id": "test.ecommerce_orders_analytics.not_null_int_weekly_order_revenue_week_start.1aa7bbdc16", "compiled": true, "compiled_code": "\n    \n    \n\n\n\nselect week_start\nfrom \"ecommerce_orders_analytics\".\"analytics\".\"int_weekly_order_revenue\"\nwhere week_start is null\n\n\n", "relation_name": null, "batch_results": null}, {"status": "pass", "timing": [{"name": "compile", "started_at": "2026-01-12T19:39:56.597899Z", "completed_at": "2026-01-12T19:39:56.597899Z"}, {"name": "execute", "started_at": "2026-01-12T19:39:56.597899Z", "completed_at": "2026-01-12T19:39:56.691649Z"}], "thread_id": "Thread-1 (worker)", "execution_time": 0.10934185981750488, "adapter_response": {"_message": "SELECT 1", "code": "SELECT", "rows_affected": 1}, "message": null, "failures": 0, "unique_id": "test.ecommerce_orders_analytics.not_null_int_weekly_order_revenue_weekly_revenue.c94c16c386", "compiled": true, "compiled_code": "\n    \n    \n\n\n\nselect weekly_revenue\nfrom \"ecommerce_orders_analytics\".\"analytics\".\"int_weekly_order_revenue\"\nwhere weekly_revenue is null\n\n\n", "relation_name": null, "batch_results": null}, {"status": "pass", "timing": [{"name": "compile", "started_at": "2026-01-12T19:39:56.707283Z", "completed_at": "2026-01-12T19:39:56.722912Z"}, {"name": "execute", "started_at": "2026-01-12T19:39:56.722912Z", "completed_at": "2026-01-12T19:39:56.816649Z"}], "thread_id": "Thread-1 (worker)", "execution_time": 0.10936617851257324, "adapter_response": {"_message": "SELECT 1", "code": "SELECT", "rows_affected": 1}, "message": null, "failures": 0, "unique_id": "test.ecommerce_orders_analytics.not_null_int_wow_order_revenue_cv_4w_week_start.f44c208548", "compiled": true, "compiled_code": "\n    \n    \n\n\n\nselect week_start\nfrom \"ecommerce_orders_analytics\".\"analytics\".\"int_wow_order_revenue_cv_4w\"\nwhere week_start is null\n\n\n", "relation_name": null, "batch_results": null}, {"status": "pass", "timing": [{"name": "compile", "started_at": "2026-01-12T19:39:56.832278Z", "completed_at": "2026-01-12T19:39:56.847900Z"}, {"name": "execute", "started_at": "2026-01-12T19:39:56.847900Z", "completed_at": "2026-01-12T19:39:57.035432Z"}], "thread_id": "Thread-1 (worker)", "execution_time": 0.21878814697265625, "adapter_response": {"_message": "SELECT 1", "code": "SELECT", "rows_affected": 1}, "message": null, "failures": 0, "unique_id": "test.ecommerce_orders_analytics.not_null_int_wow_order_revenue_cv_4w_weekly_revenue.26e6ee6c8b", "compiled": true, "compiled_code": "\n    \n    \n\n\n\nselect weekly_revenue\nfrom \"ecommerce_orders_analytics\".\"analytics\".\"int_wow_order_revenue_cv_4w\"\nwhere weekly_revenue is null\n\n\n", "relation_name": null, "batch_results": null}, {"status": "pass", "timing": [{"name": "compile", "started_at": "2026-01-12T19:39:57.051067Z", "completed_at": "2026-01-12T19:39:57.066656Z"}, {"name": "execute", "started_at": "2026-01-12T19:39:57.066656Z", "completed_at": "2026-01-12T19:39:57.160431Z"}], "thread_id": "Thread-1 (worker)", "execution_time": 0.10936474800109863, "adapter_response": {"_message": "SELECT 1", "code": "SELECT", "rows_affected": 1}, "message": null, "failures": 0, "unique_id": "test.ecommerce_orders_analytics.not_null_int_wow_order_revenue_growth_ratio_week_start.ea12aafa23", "compiled": true, "compiled_code": "\n    \n    \n\n\n\nselect week_start\nfrom \"ecommerce_orders_analytics\".\"analytics\".\"int_wow_order_revenue_growth_ratio\"\nwhere week_start is null\n\n\n", "relation_name": null, "batch_results": null}, {"status": "pass", "timing": [{"name": "compile", "started_at": "2026-01-12T19:39:57.176025Z", "completed_at": "2026-01-12T19:39:57.191666Z"}, {"name": "execute", "started_at": "2026-01-12T19:39:57.191666Z", "completed_at": "2026-01-12T19:39:57.285435Z"}], "thread_id": "Thread-1 (worker)", "execution_time": 0.10940980911254883, "adapter_response": {"_message": "SELECT 1", "code": "SELECT", "rows_affected": 1}, "message": null, "failures": 0, "unique_id": "test.ecommerce_orders_analytics.not_null_int_wow_order_revenue_growth_ratio_weekly_revenue.211bee1fa6", "compiled": true, "compiled_code": "\n    \n    \n\n\n\nselect weekly_revenue\nfrom \"ecommerce_orders_analytics\".\"analytics\".\"int_wow_order_revenue_growth_ratio\"\nwhere weekly_revenue is null\n\n\n", "relation_name": null, "batch_results": null}, {"status": "pass", "timing": [{"name": "compile", "started_at": "2026-01-12T19:39:57.301033Z", "completed_at": "2026-01-12T19:39:57.301033Z"}, {"name": "execute", "started_at": "2026-01-12T19:39:57.301033Z", "completed_at": "2026-01-12T19:39:57.394774Z"}], "thread_id": "Thread-1 (worker)", "execution_time": 0.10933876037597656, "adapter_response": {"_message": "SELECT 1", "code": "SELECT", "rows_affected": 1}, "message": null, "failures": 0, "unique_id": "test.ecommerce_orders_analytics.not_null_staging_orders_cleaned_amount.8759b2461a", "compiled": true, "compiled_code": "\n    \n    \n\n\n\nselect cleaned_amount\nfrom \"ecommerce_orders_analytics\".\"analytics\".\"staging_orders\"\nwhere cleaned_amount is null\n\n\n", "relation_name": null, "batch_results": null}, {"status": "pass", "timing": [{"name": "compile", "started_at": "2026-01-12T19:39:57.410402Z", "completed_at": "2026-01-12T19:39:57.426036Z"}, {"name": "execute", "started_at": "2026-01-12T19:39:57.426036Z", "completed_at": "2026-01-12T19:39:57.519809Z"}], "thread_id": "Thread-1 (worker)", "execution_time": 0.10940670967102051, "adapter_response": {"_message": "SELECT 1", "code": "SELECT", "rows_affected": 1}, "message": null, "failures": 0, "unique_id": "test.ecommerce_orders_analytics.not_null_staging_orders_customer_id.7a00baf784", "compiled": true, "compiled_code": "\n    \n    \n\n\n\nselect customer_id\nfrom \"ecommerce_orders_analytics\".\"analytics\".\"staging_orders\"\nwhere customer_id is null\n\n\n", "relation_name": null, "batch_results": null}, {"status": "pass", "timing": [{"name": "compile", "started_at": "2026-01-12T19:39:57.535401Z", "completed_at": "2026-01-12T19:39:57.551041Z"}, {"name": "execute", "started_at": "2026-01-12T19:39:57.551041Z", "completed_at": "2026-01-12T19:39:57.644809Z"}], "thread_id": "Thread-1 (worker)", "execution_time": 0.10940790176391602, "adapter_response": {"_message": "SELECT 1", "code": "SELECT", "rows_affected": 1}, "message": null, "failures": 0, "unique_id": "test.ecommerce_orders_analytics.not_null_staging_orders_order_id.d83be3d6de", "compiled": true, "compiled_code": "\n    \n    \n\n\n\nselect order_id\nfrom \"ecommerce_orders_analytics\".\"analytics\".\"staging_orders\"\nwhere order_id is null\n\n\n", "relation_name": null, "batch_results": null}, {"status": "pass", "timing": [{"name": "compile", "started_at": "2026-01-12T19:39:57.660407Z", "completed_at": "2026-01-12T19:39:57.660407Z"}, {"name": "execute", "started_at": "2026-01-12T19:39:57.660407Z", "completed_at": "2026-01-12T19:39:57.754149Z"}], "thread_id": "Thread-1 (worker)", "execution_time": 0.09374213218688965, "adapter_response": {"_message": "SELECT 1", "code": "SELECT", "rows_affected": 1}, "message": null, "failures": 0, "unique_id": "test.ecommerce_orders_analytics.not_null_staging_orders_week_start.66ee82834b", "compiled": true, "compiled_code": "\n    \n    \n\n\n\nselect week_start\nfrom \"ecommerce_orders_analytics\".\"analytics\".\"staging_orders\"\nwhere week_start is null\n\n\n", "relation_name": null, "batch_results": null}, {"status": "pass", "timing": [{"name": "compile", "started_at": "2026-01-12T19:39:57.769777Z", "completed_at": "2026-01-12T19:39:57.785409Z"}, {"name": "execute", "started_at": "2026-01-12T19:39:57.785409Z", "completed_at": "2026-01-12T19:39:57.879150Z"}], "thread_id": "Thread-1 (worker)", "execution_time": 0.10937237739562988, "adapter_response": {"_message": "SELECT 1", "code": "SELECT", "rows_affected": 1}, "message": null, "failures": 0, "unique_id": "test.ecommerce_orders_analytics.unique_fact_order_revenue_consistency_week_start.91efb18f19", "compiled": true, "compiled_code": "\n    \n    \n\nselect\n    week_start as unique_field,\n    count(*) as n_records\n\nfrom \"ecommerce_orders_analytics\".\"analytics\".\"fact_order_revenue_consistency\"\nwhere week_start is not null\ngroup by week_start\nhaving count(*) > 1\n\n\n", "relation_name": null, "batch_results": null}, {"status": "pass", "timing": [{"name": "compile", "started_at": "2026-01-12T19:39:57.894776Z", "completed_at": "2026-01-12T19:39:57.910402Z"}, {"name": "execute", "started_at": "2026-01-12T19:39:57.910402Z", "completed_at": "2026-01-12T19:39:58.004149Z"}], "thread_id": "Thread-1 (worker)", "execution_time": 0.10937309265136719, "adapter_response": {"_message": "SELECT 1", "code": "SELECT", "rows_affected": 1}, "message": null, "failures": 0, "unique_id": "test.ecommerce_orders_analytics.unique_fact_order_weekly_growth_week_start.862af746da", "compiled": true, "compiled_code": "\n    \n    \n\nselect\n    week_start as unique_field,\n    count(*) as n_records\n\nfrom \"ecommerce_orders_analytics\".\"analytics\".\"fact_order_weekly_growth\"\nwhere week_start is not null\ngroup by week_start\nhaving count(*) > 1\n\n\n", "relation_name": null, "batch_results": null}, {"status": "pass", "timing": [{"name": "compile", "started_at": "2026-01-12T19:39:58.019776Z", "completed_at": "2026-01-12T19:39:58.035407Z"}, {"name": "execute", "started_at": "2026-01-12T19:39:58.035407Z", "completed_at": "2026-01-12T19:39:58.222904Z"}], "thread_id": "Thread-1 (worker)", "execution_time": 0.21875452995300293, "adapter_response": {"_message": "SELECT 1", "code": "SELECT", "rows_affected": 1}, "message": null, "failures": 0, "unique_id": "test.ecommerce_orders_analytics.unique_int_weekly_customers_churned_customers_week.839a40c715", "compiled": true, "compiled_code": "\n    \n    \n\nselect\n    week as unique_field,\n    count(*) as n_records\n\nfrom \"ecommerce_orders_analytics\".\"analytics\".\"int_weekly_customers_churned_customers\"\nwhere week is not null\ngroup by week\nhaving count(*) > 1\n\n\n", "relation_name": null, "batch_results": null}, {"status": "pass", "timing": [{"name": "compile", "started_at": "2026-01-12T19:39:58.238530Z", "completed_at": "2026-01-12T19:39:58.254162Z"}, {"name": "execute", "started_at": "2026-01-12T19:39:58.254162Z", "completed_at": "2026-01-12T19:39:58.347900Z"}], "thread_id": "Thread-1 (worker)", "execution_time": 0.10936951637268066, "adapter_response": {"_message": "SELECT 1", "code": "SELECT", "rows_affected": 1}, "message": null, "failures": 0, "unique_id": "test.ecommerce_orders_analytics.unique_int_weekly_customers_retained_customers_week.a2b7528baf", "compiled": true, "compiled_code": "\n    \n    \n\nselect\n    week as unique_field,\n    count(*) as n_records\n\nfrom \"ecommerce_orders_analytics\".\"analytics\".\"int_weekly_customers_retained_customers\"\nwhere week is not null\ngroup by week\nhaving count(*) > 1\n\n\n", "relation_name": null, "batch_results": null}, {"status": "pass", "timing": [{"name": "compile", "started_at": "2026-01-12T19:39:58.363531Z", "completed_at": "2026-01-12T19:39:58.379160Z"}, {"name": "execute", "started_at": "2026-01-12T19:39:58.379160Z", "completed_at": "2026-01-12T19:39:58.472938Z"}], "thread_id": "Thread-1 (worker)", "execution_time": 0.1094064712524414, "adapter_response": {"_message": "SELECT 1", "code": "SELECT", "rows_affected": 1}, "message": null, "failures": 0, "unique_id": "test.ecommerce_orders_analytics.unique_int_weekly_order_revenue_week_start.90b99ff027", "compiled": true, "compiled_code": "\n    \n    \n\nselect\n    week_start as unique_field,\n    count(*) as n_records\n\nfrom \"ecommerce_orders_analytics\".\"analytics\".\"int_weekly_order_revenue\"\nwhere week_start is not null\ngroup by week_start\nhaving count(*) > 1\n\n\n", "relation_name": null, "batch_results": null}, {"status": "pass", "timing": [{"name": "compile", "started_at": "2026-01-12T19:39:58.488537Z", "completed_at": "2026-01-12T19:39:58.488537Z"}, {"name": "execute", "started_at": "2026-01-12T19:39:58.488537Z", "completed_at": "2026-01-12T19:39:58.676055Z"}], "thread_id": "Thread-1 (worker)", "execution_time": 0.21872520446777344, "adapter_response": {"_message": "SELECT 1", "code": "SELECT", "rows_affected": 1}, "message": null, "failures": 0, "unique_id": "test.ecommerce_orders_analytics.unique_staging_orders_order_id.81f14eb898", "compiled": true, "compiled_code": "\n    \n    \n\nselect\n    order_id as unique_field,\n    count(*) as n_records\n\nfrom \"ecommerce_orders_analytics\".\"analytics\".\"staging_orders\"\nwhere order_id is not null\ngroup by order_id\nhaving count(*) > 1\n\n\n", "relation_name": null, "batch_results": null}], "elapsed_time": 6.618812084197998, "args": {"project_dir": "C:\\emp_analytics\\ecommerce_orders_analytics", "require_unique_project_resource_names": false, "resource_types": [], "invocation_command": "dbt test", "show_resource_report": false, "use_fast_test_edges": false, "indirect_selection": "eager", "select": [], "favor_state": false, "state_modified_compare_vars": false, "strict_mode": false, "log_path": "C:\\emp_analytics\\ecommerce_orders_analytics\\logs", "quiet": false, "vars": {}, "require_resource_names_without_spaces": true, "version_check": true, "log_format_file": "debug", "log_level": "info", "defer": false, "skip_nodes_if_on_run_start_fails": false, "write_json": true, "warn_error_options": {"error": [], "warn": [], "silence": []}, "require_ref_searches_node_package_before_root": false, "require_yaml_configuration_for_mf_time_spines": false, "cache_selected_only": false, "require_batched_execution_for_custom_microbatch_strategy": false, "require_explicit_package_overrides_for_builtin_materializations": true, "log_file_max_bytes": 10485760, "print": true, "show_all_deprecations": false, "which": "test", "partial_parse": true, "introspect": true, "source_freshness_run_project_hooks": true, "send_anonymous_usage_stats": true, "log_level_file": "debug", "exclude": [], "macro_debugging": false, "profiles_dir": "C:\\Users\\mayur\\AppData\\Roaming\\dbt", "require_generic_test_arguments_property": true, "printer_width": 80, "exclude_resource_types": [], "partial_parse_file_diff": true, "validate_macro_args": false, "require_all_warnings_handled_by_warn_error": false, "use_colors_file": true, "use_colors": true, "upload_to_artifacts_ingest_api": false, "require_nested_cumulative_type_params": false, "log_format": "default", "populate_cache": true, "static_parser": true, "state_modified_compare_more_unrendered_values": false}}